{
	"info": {
		"_postman_id": "1a332150-b180-4f43-a6bf-26d7f1bb5fb0",
		"name": "api-Activities",
		"schema": "https://schema.getpostman.com/json/collection/v2.1.0/collection.json",
		"_exporter_id": "21580260"
	},
	"item": [
		{
			"name": "get-activities",
			"request": {
				"method": "GET",
				"header": [
					{
						"key": "accept",
						"value": "text/plain; v=1.0"
					}
				],
				"url": {
					"raw": "https://fakerestapi.azurewebsites.net/api/v1/Activities",
					"protocol": "https",
					"host": [
						"fakerestapi",
						"azurewebsites",
						"net"
					],
					"path": [
						"api",
						"v1",
						"Activities"
					]
				}
			},
			"response": []
		}
	]
}